kage/__init__.py
kage-0.0.1.dist-info/DESCRIPTION.rst
kage-0.0.1.dist-info/METADATA
kage-0.0.1.dist-info/RECORD
kage-0.0.1.dist-info/WHEEL
kage-0.0.1.dist-info/entry_points.txt
kage-0.0.1.dist-info/metadata.json
kage-0.0.1.dist-info/top_level.txt
